LICENSE
MANIFEST.in
README.rst
setup.py
bootstrap3_datepicker/__init__.py
bootstrap3_datepicker/fields.py
bootstrap3_datepicker/widgets.py
bootstrap3_datepicker/static/bootstrap3_datepicker/css/bootstrap-datepicker3.css
bootstrap3_datepicker/static/bootstrap3_datepicker/css/bootstrap-datepicker3.min.css
bootstrap3_datepicker/static/bootstrap3_datepicker/js/bootstrap-datepicker.js
bootstrap3_datepicker/static/bootstrap3_datepicker/js/bootstrap-datepicker.min.js
bootstrap3_datepicker/static/bootstrap3_datepicker/locales/bootstrap-datepicker.ar.min.js
bootstrap3_datepicker/static/bootstrap3_datepicker/locales/bootstrap-datepicker.az.min.js
bootstrap3_datepicker/static/bootstrap3_datepicker/locales/bootstrap-datepicker.bg.min.js
bootstrap3_datepicker/static/bootstrap3_datepicker/locales/bootstrap-datepicker.bs.min.js
bootstrap3_datepicker/static/bootstrap3_datepicker/locales/bootstrap-datepicker.ca.min.js
bootstrap3_datepicker/static/bootstrap3_datepicker/locales/bootstrap-datepicker.cs.min.js
bootstrap3_datepicker/static/bootstrap3_datepicker/locales/bootstrap-datepicker.cy.min.js
bootstrap3_datepicker/static/bootstrap3_datepicker/locales/bootstrap-datepicker.da.min.js
bootstrap3_datepicker/static/bootstrap3_datepicker/locales/bootstrap-datepicker.de.min.js
bootstrap3_datepicker/static/bootstrap3_datepicker/locales/bootstrap-datepicker.el.min.js
bootstrap3_datepicker/static/bootstrap3_datepicker/locales/bootstrap-datepicker.en-AU.min.js
bootstrap3_datepicker/static/bootstrap3_datepicker/locales/bootstrap-datepicker.en-GB.min.js
bootstrap3_datepicker/static/bootstrap3_datepicker/locales/bootstrap-datepicker.eo.min.js
bootstrap3_datepicker/static/bootstrap3_datepicker/locales/bootstrap-datepicker.es.min.js
bootstrap3_datepicker/static/bootstrap3_datepicker/locales/bootstrap-datepicker.et.min.js
bootstrap3_datepicker/static/bootstrap3_datepicker/locales/bootstrap-datepicker.eu.min.js
django_bootstrap3_datepicker.egg-info/PKG-INFO
django_bootstrap3_datepicker.egg-info/SOURCES.txt
django_bootstrap3_datepicker.egg-info/dependency_links.txt
django_bootstrap3_datepicker.egg-info/top_level.txt