Metadata-Version: 1.1
Name: django-bootstrap3-datepicker
Version: 0.4.1
Summary: Bootstrap3 compatible datepicker for Django projects.
Home-page: https://github.com/qoobic/django-bootstrap3-datepicker.git
Author: James Hargreaves
Author-email: james.hargreaves@qoobic.co.uk
License: Apache License 2.0
Platform: UNKNOWN
Classifier: Intended Audience :: Developers
Classifier: License :: OSI Approved :: Apache Software License
Classifier: Programming Language :: Python
Classifier: Programming Language :: Python :: 2
Classifier: Programming Language :: Python :: 3
Classifier: Operating System :: OS Independent
Classifier: Topic :: Software Development :: Libraries
Classifier: Topic :: Utilities
Classifier: Environment :: Web Environment
Classifier: Framework :: Django
